articraft/__init__.py
articraft/__main__.py
articraft/logger.py
articraft/urls.py
articraft/.abcli/ComfyUI.sh
articraft/.abcli/abcli.sh
articraft/.abcli/actions.sh
articraft/.abcli/aiart.sh
articraft/.abcli/aka.sh
articraft/.abcli/generate.sh
articraft/.abcli/html.sh
articraft/.abcli/publish.sh
articraft/.abcli/transform.sh
articraft/.abcli/urllib.sh
articraft/.abcli/ComfyUI/install.sh
articraft/.abcli/ComfyUI/start.sh
articraft/.abcli/ComfyUI/tunnel.sh
articraft/.abcli/ComfyUI/uninstall.sh
articraft/.abcli/generate/image.sh
articraft/.abcli/generate/validate.sh
articraft/.abcli/generate/video.sh
articraft/.abcli/tests/version.sh
articraft-2.79.1.dist-info/LICENSE
articraft-2.79.1.dist-info/METADATA
articraft-2.79.1.dist-info/WHEEL
articraft-2.79.1.dist-info/top_level.txt
articraft-2.79.1.dist-info/RECORD
