Metadata-Version: 2.1
Name: articraft
Version: 2.79.1
Summary: 🎨 tools for ai artists.
Home-page: https://github.com/kamangir/aiart
Author: Arash Abadpour (Kamangir)
Author-email: arash@kamangir.net
License: Public Domain
Classifier: Programming Language :: Python :: 3
Classifier: Programming Language :: Unix Shell
Classifier: License :: Public Domain
Classifier: Operating System :: OS Independent
License-File: LICENSE
Requires-Dist: blueness
Requires-Dist: abcli
Requires-Dist: beautifulsoup4
Requires-Dist: boto3
Requires-Dist: folium
Requires-Dist: geojson
Requires-Dist: geopandas
Requires-Dist: matplotlib
Requires-Dist: opencv-python
Requires-Dist: pymysql
Requires-Dist: pyyaml
Requires-Dist: pylint
Requires-Dist: pyngrok
Requires-Dist: pytest
Requires-Dist: python-dotenv[cli]
Requires-Dist: requests
Requires-Dist: tqdm
